pygrister/__init__.py
pygrister/_pygrystart.py
pygrister/api.py
pygrister/apicaller.py
pygrister/cli.py
pygrister/config.py
pygrister/exceptions.py
pygrister-0.9.1.dist-info/licenses/LICENSE.txt
pygrister-0.9.1.dist-info/METADATA
pygrister-0.9.1.dist-info/WHEEL
pygrister-0.9.1.dist-info/entry_points.txt
pygrister-0.9.1.dist-info/top_level.txt
pygrister-0.9.1.dist-info/RECORD
