Metadata-Version: 2.4
Name: Pygrister
Version: 0.9.1
Summary: A Python client for the Grist API.
Author: Riccardo Polignieri
License-Expression: MIT
Project-URL: Repository, https://github.com/ricpol/pygrister
Project-URL: Bug Tracker, https://github.com/ricpol/pygrister/issues
Project-URL: Changelog, https://github.com/ricpol/pygrister/blob/main/NEWS.txt
Project-URL: Documentation, https://pygrister.readthedocs.io
Keywords: Grist,relational spreadsheet,database,API
Classifier: Development Status :: 4 - Beta
Classifier: Intended Audience :: Developers
Classifier: Topic :: Software Development :: Libraries
Classifier: Topic :: Database
Classifier: Programming Language :: Python :: 3
Classifier: Programming Language :: Python :: 3.9
Classifier: Programming Language :: Python :: 3.10
Classifier: Programming Language :: Python :: 3.11
Classifier: Programming Language :: Python :: 3.12
Classifier: Programming Language :: Python :: 3.13
Requires-Python: >=3.9
License-File: LICENSE.txt
Requires-Dist: requests>=2.31.0
Requires-Dist: typer>=0.15.0
Dynamic: license-file
